src/osmchange_generator_cli/__init__.py
src/osmchange_generator_cli/main.py
osmchange_generator_cli-0.2.0.dist-info/entry_points.txt
osmchange_generator_cli-0.2.0.dist-info/licenses/LICENSE
osmchange_generator_cli-0.2.0.dist-info/METADATA
osmchange_generator_cli-0.2.0.dist-info/WHEEL
osmchange_generator_cli-0.2.0.dist-info/RECORD
