Metadata-Version: 2.4
Name: osmchange_generator_cli
Version: 0.2.0
Summary: OsmChange file generator useful for importing and updating data in OpenStreetMap.
License: MIT
License-File: LICENSE
Keywords: openstreetmap,osm,OsmChange,generator,cli
Author: Christopher Kwiatkowski
Requires-Python: >= 3.10
Classifier: Development Status :: 3 - Alpha
Classifier: Environment :: Console
Classifier: License :: OSI Approved :: MIT License
Classifier: Natural Language :: English
Classifier: Programming Language :: Python :: 3
Classifier: Programming Language :: Python :: 3.10
Classifier: Programming Language :: Python :: 3.11
Classifier: Programming Language :: Python :: 3.12
Classifier: Programming Language :: Python :: 3.13
Classifier: Programming Language :: Python :: 3.14
Classifier: Programming Language :: Python :: 3 :: Only
Requires-Dist: osm-easy-api (==3.0.2)
Requires-Dist: typer (==0.19.2)
Project-URL: Homepage, https://github.com/docentYT/OsmChange-generator-cli
Project-URL: Repository, https://github.com/docentYT/OsmChange-generator-cli
